dyntrace/__init__.py
dyntrace/training/lstm.py
dyntrace/training/tcn.py
dyntrace/utility/__init__.py
dyntrace/utility/csmip.py
dyntrace/utility/evaluate.py
dyntrace-0.0.2.dist-info/METADATA
dyntrace-0.0.2.dist-info/WHEEL
dyntrace-0.0.2.dist-info/top_level.txt
dyntrace-0.0.2.dist-info/RECORD
