Metadata-Version: 2.1
Name: dyntrace
Version: 0.0.2
Summary: Dynamic Time-series Response Analysis and Computational Estimation
Author-email: Issac Pang <issac.pang@berkeley.edu>
Project-URL: Repository, http://github.com/issacpang/dyntrace
Keywords: seismic,earthquake
Requires-Dist: numpy
Requires-Dist: scipy
Requires-Dist: sympy
Requires-Dist: keras
Requires-Dist: pydot
Requires-Dist: seaborn
Requires-Dist: tensorflow
Requires-Dist: pandas
Requires-Dist: scikit-learn
Requires-Dist: opensees
